Workbook

Sheet Cover
B3: ETERNAL LIMITED (ZOMATO)
B4: Discounted Cash Flow (DCF) Valuation Model
B5: 3-Statement-Linked Model | Scenario & Sensitivity Analysis
B10: NSE / BSE: ETERNAL | 543320 Sector: Consumer Internet — Food Delivery, Quick Commerce & B2B Supplies
B12: Prepared by: | C12: Debayan Bandyopadhyay
B13: Prepared for: | C13: Portfolio Project (FMVA)
B14: Valuation date: | C14: 24-September-2026
B15: Currency / units: | C15: Indian Rupees, in Crore (₹ Cr), unless stated otherwise
B16: Valuation method: | C16: Unlevered FCFF DCF — Gordon Growth + Exit Multiple cross-check; FY27 includes Q1 actual run-rate calibration
B17: Scenarios modeled: | C17: Bear Case | Base Case | Bull Case — fully linked, driver-based
B19: Workbook contents
B20: 1. Cover | C20: This page — model scope, author & navigation
B21: 2. Output | C21: Valuation summary, scenario comparison, sensitivity tables & charts
B22: 3. Inputs | C22: All hardcoded assumptions (blue) — company data, WACC build, 3-scenario drivers
B23: 4. Model | C23: Fully-linked operating schedules: revenue, cost, D&A, debt, tax, FCFF, DCF — for each scenario
B24: 5. Sources | C24: Assumption audit, source list, v1.1 changes and known limitations
B25: Formatting convention
B26: Blue font | C26: Hardcoded inputs / assumptions — the only cells that should be edited
B27: Black font | C27: Formulas / calculated outputs — fully linked, do not hardcode over these
B29: Disclaimer: This model is for academic and interview purposes and uses publicly available information on Eternal Ltd. Historical figures are sourced from company disclosures and market data; forecast assumptions are my own estimates. This is not investment research or a recommendation. Check the latest company filings before using the model for any investment decision.

Sheet Output
A1: ETERNAL LTD (ZOMATO) — DCF VALUATION: OUTPUT SUMMARY (₹ Crore unless stated)
A2: AT A GLANCE | B2: =Inputs!$B$39 | C2: =Model!C53 | D2: =Model!C54 | E2: =Model!C55 | F2: =Model!C57 | G2: =(Model!I5/Model!B5)^(1/7)-1
B3: WACC | C3: BASE PX — GORDON GROWTH | D3: BASE PX — EXIT MULTIPLE | E3: CURRENT MARKET PRICE | F3: BASE UPSIDE — EXIT MULT. | G3: BASE REVENUE CAGR FY26A-33E | J3: Chart data (linked — do not delete)
J4: Year | K4: FY26A | L4: FY27E | M4: FY28E | N4: FY29E | O4: FY30E | P4: FY31E | Q4: FY32E | R4: FY33E
A5: A. SCENARIO COMPARISON — BEAR | BASE | BULL | J5: Revenue — Base (₹ Cr) | K5: =Model!B5 | L5: =Model!C5 | M5: =Model!D5 | N5: =Model!E5 | O5: =Model!F5 | P5: =Model!G5 | Q5: =Model!H5 | R5: =Model!I5
A6: Metric | B6: Bear Case | C6: Base Case | D6: Bull Case | J6: EBITDA margin — Base (%) | K6: =Model!B14 | L6: =Model!C14 | M6: =Model!D14 | N6: =Model!E14 | O6: =Model!F14 | P6: =Model!G14 | Q6: =Model!H14 | R6: =Model!I14
A7: Revenue FY33E | B7: =Model!I119 | C7: =Model!I5 | D7: =Model!I62
A8: EBITDA FY33E | B8: =Model!I127 | C8: =Model!I13 | D8: =Model!I70 | J8: Year (forecast only) | K8: FY27E | L8: FY28E | M8: FY29E | N8: FY30E | O8: FY31E | P8: FY32E | Q8: FY33E
A9: EBITDA margin FY33E | B9: =Model!I128 | C9: =Model!I14 | D9: =Model!I71 | J9: FCFF — Bear (₹ Cr) | K9: =Model!C144 | L9: =Model!D144 | M9: =Model!E144 | N9: =Model!F144 | O9: =Model!G144 | P9: =Model!H144 | Q9: =Model!I144
A10: FCFF FY33E | B10: =Model!I144 | C10: =Model!I30 | D10: =Model!I87 | J10: FCFF — Base (₹ Cr) | K10: =Model!C30 | L10: =Model!D30 | M10: =Model!E30 | N10: =Model!F30 | O10: =Model!G30 | P10: =Model!H30 | Q10: =Model!I30
A11: Revenue CAGR FY26A-FY33E | B11: =(Model!I119/Model!B119)^(1/7)-1 | C11: =(Model!I5/Model!B5)^(1/7)-1 | D11: =(Model!I62/Model!B62)^(1/7)-1 | J11: FCFF — Bull (₹ Cr) | K11: =Model!C87 | L11: =Model!D87 | M11: =Model!E87 | N11: =Model!F87 | O11: =Model!G87 | P11: =Model!H87 | Q11: =Model!I87
A13: Enterprise Value — Gordon Growth | B13: =Model!C161 | C13: =Model!C47 | D13: =Model!C104
A14: Enterprise Value — Exit Multiple | B14: =Model!C162 | C14: =Model!C48 | D14: =Model!C105
A15: Equity Value — Gordon Growth | B15: =Model!C164 | C15: =Model!C50 | D15: =Model!C107
A16: Equity Value — Exit Multiple | B16: =Model!C165 | C16: =Model!C51 | D16: =Model!C108
A18: Implied Share Price — Gordon Growth (₹) | B18: =Model!C167 | C18: =Model!C53 | D18: =Model!C110
A19: Implied Share Price — Exit Multiple (₹) | B19: =Model!C168 | C19: =Model!C54 | D19: =Model!C111
A20: Current Market Price (₹) | B20: =Model!C169 | C20: =Model!C55 | D20: =Model!C112
A21: Upside/(Downside) — Gordon Growth | B21: =Model!C170 | C21: =Model!C56 | D21: =Model!C113
A22: Upside/(Downside) — Exit Multiple | B22: =Model!C171 | C22: =Model!C57 | D22: =Model!C114
A24: B. DISCOUNT RATE & TERMINAL VALUE ASSUMPTIONS RECAP
A25: WACC (single rate, all scenarios) | B25: =Inputs!$B$39
A26: Cost of equity (CAPM) | B26: =Inputs!$B$31
A27: Terminal growth rate (g) | B27: =Inputs!$C$81 | C27: =Inputs!$C$57 | D27: =Inputs!$C$69
A28: Exit EV/EBITDA multiple | B28: =Inputs!$C$82 | C28: =Inputs!$C$58 | D28: =Inputs!$C$70
A30: C. SENSITIVITY — IMPLIED SHARE PRICE (₹): WACC × TERMINAL GROWTH RATE (Gordon Growth method, Base Case cash flows)
A31: Rows = WACC (± around base WACC); Columns = terminal growth g (± around base g). Formula: (NPV(WACC, Base-case FCFF FY27E-FY33E) + [FCFF FY33E×(1+g)/(WACC-g)] / (1+WACC)^7 − Net debt) / Diluted shares.
A32: WACC \ Terminal g | B32: =Inputs!$C$57-0.01 | C32: =Inputs!$C$57-0.005 | D32: =Inputs!$C$57 | E32: =Inputs!$C$57+0.005 | F32: =Inputs!$C$57+0.01
A33: =Inputs!$B$39-0.02 | B33: =(NPV($A33,Model!$C$30:$I$30)+(Model!$I$30*(1+B$32)/($A33-B$32))/(1+$A33)^7-Inputs!$B$25)/Inputs!$B$8 | C33: =(NPV($A33,Model!$C$30:$I$30)+(Model!$I$30*(1+C$32)/($A33-C$32))/(1+$A33)^7-Inputs!$B$25)/Inputs!$B$8 | D33: =(NPV($A33,Model!$C$30:$I$30)+(Model!$I$30*(1+D$32)/($A33-D$32))/(1+$A33)^7-Inputs!$B$25)/Inputs!$B$8 | E33: =(NPV($A33,Model!$C$30:$I$30)+(Model!$I$30*(1+E$32)/($A33-E$32))/(1+$A33)^7-Inputs!$B$25)/Inputs!$B$8 | F33: =(NPV($A33,Model!$C$30:$I$30)+(Model!$I$30*(1+F$32)/($A33-F$32))/(1+$A33)^7-Inputs!$B$25)/Inputs!$B$8
A34: =Inputs!$B$39-0.01 | B34: =(NPV($A34,Model!$C$30:$I$30)+(Model!$I$30*(1+B$32)/($A34-B$32))/(1+$A34)^7-Inputs!$B$25)/Inputs!$B$8 | C34: =(NPV($A34,Model!$C$30:$I$30)+(Model!$I$30*(1+C$32)/($A34-C$32))/(1+$A34)^7-Inputs!$B$25)/Inputs!$B$8 | D34: =(NPV($A34,Model!$C$30:$I$30)+(Model!$I$30*(1+D$32)/($A34-D$32))/(1+$A34)^7-Inputs!$B$25)/Inputs!$B$8 | E34: =(NPV($A34,Model!$C$30:$I$30)+(Model!$I$30*(1+E$32)/($A34-E$32))/(1+$A34)^7-Inputs!$B$25)/Inputs!$B$8 | F34: =(NPV($A34,Model!$C$30:$I$30)+(Model!$I$30*(1+F$32)/($A34-F$32))/(1+$A34)^7-Inputs!$B$25)/Inputs!$B$8
A35: =Inputs!$B$39 | B35: =(NPV($A35,Model!$C$30:$I$30)+(Model!$I$30*(1+B$32)/($A35-B$32))/(1+$A35)^7-Inputs!$B$25)/Inputs!$B$8 | C35: =(NPV($A35,Model!$C$30:$I$30)+(Model!$I$30*(1+C$32)/($A35-C$32))/(1+$A35)^7-Inputs!$B$25)/Inputs!$B$8 | D35: =(NPV($A35,Model!$C$30:$I$30)+(Model!$I$30*(1+D$32)/($A35-D$32))/(1+$A35)^7-Inputs!$B$25)/Inputs!$B$8 | E35: =(NPV($A35,Model!$C$30:$I$30)+(Model!$I$30*(1+E$32)/($A35-E$32))/(1+$A35)^7-Inputs!$B$25)/Inputs!$B$8 | F35: =(NPV($A35,Model!$C$30:$I$30)+(Model!$I$30*(1+F$32)/($A35-F$32))/(1+$A35)^7-Inputs!$B$25)/Inputs!$B$8
A36: =Inputs!$B$39+0.01 | B36: =(NPV($A36,Model!$C$30:$I$30)+(Model!$I$30*(1+B$32)/($A36-B$32))/(1+$A36)^7-Inputs!$B$25)/Inputs!$B$8 | C36: =(NPV($A36,Model!$C$30:$I$30)+(Model!$I$30*(1+C$32)/($A36-C$32))/(1+$A36)^7-Inputs!$B$25)/Inputs!$B$8 | D36: =(NPV($A36,Model!$C$30:$I$30)+(Model!$I$30*(1+D$32)/($A36-D$32))/(1+$A36)^7-Inputs!$B$25)/Inputs!$B$8 | E36: =(NPV($A36,Model!$C$30:$I$30)+(Model!$I$30*(1+E$32)/($A36-E$32))/(1+$A36)^7-Inputs!$B$25)/Inputs!$B$8 | F36: =(NPV($A36,Model!$C$30:$I$30)+(Model!$I$30*(1+F$32)/($A36-F$32))/(1+$A36)^7-Inputs!$B$25)/Inputs!$B$8
A37: =Inputs!$B$39+0.02 | B37: =(NPV($A37,Model!$C$30:$I$30)+(Model!$I$30*(1+B$32)/($A37-B$32))/(1+$A37)^7-Inputs!$B$25)/Inputs!$B$8 | C37: =(NPV($A37,Model!$C$30:$I$30)+(Model!$I$30*(1+C$32)/($A37-C$32))/(1+$A37)^7-Inputs!$B$25)/Inputs!$B$8 | D37: =(NPV($A37,Model!$C$30:$I$30)+(Model!$I$30*(1+D$32)/($A37-D$32))/(1+$A37)^7-Inputs!$B$25)/Inputs!$B$8 | E37: =(NPV($A37,Model!$C$30:$I$30)+(Model!$I$30*(1+E$32)/($A37-E$32))/(1+$A37)^7-Inputs!$B$25)/Inputs!$B$8 | F37: =(NPV($A37,Model!$C$30:$I$30)+(Model!$I$30*(1+F$32)/($A37-F$32))/(1+$A37)^7-Inputs!$B$25)/Inputs!$B$8
A40: D. SENSITIVITY — IMPLIED SHARE PRICE (₹): WACC × EXIT EV/EBITDA MULTIPLE (Exit Multiple method, Base Case cash flows)
A41: Rows = WACC (± around base WACC); Columns = exit EV/EBITDA multiple (± around base multiple). Formula: (NPV(WACC, Base-case FCFF FY27E-FY33E) + [EBITDA FY33E × Multiple] / (1+WACC)^7 − Net debt) / Diluted shares.
A42: WACC \ Exit Multiple | B42: =Inputs!$C$58-4 | C42: =Inputs!$C$58-2 | D42: =Inputs!$C$58 | E42: =Inputs!$C$58+2 | F42: =Inputs!$C$58+4
A43: =Inputs!$B$39-0.02 | B43: =(NPV($A43,Model!$C$30:$I$30)+(Model!$I$13*B$42)/(1+$A43)^7-Inputs!$B$25)/Inputs!$B$8 | C43: =(NPV($A43,Model!$C$30:$I$30)+(Model!$I$13*C$42)/(1+$A43)^7-Inputs!$B$25)/Inputs!$B$8 | D43: =(NPV($A43,Model!$C$30:$I$30)+(Model!$I$13*D$42)/(1+$A43)^7-Inputs!$B$25)/Inputs!$B$8 | E43: =(NPV($A43,Model!$C$30:$I$30)+(Model!$I$13*E$42)/(1+$A43)^7-Inputs!$B$25)/Inputs!$B$8 | F43: =(NPV($A43,Model!$C$30:$I$30)+(Model!$I$13*F$42)/(1+$A43)^7-Inputs!$B$25)/Inputs!$B$8
A44: =Inputs!$B$39-0.01 | B44: =(NPV($A44,Model!$C$30:$I$30)+(Model!$I$13*B$42)/(1+$A44)^7-Inputs!$B$25)/Inputs!$B$8 | C44: =(NPV($A44,Model!$C$30:$I$30)+(Model!$I$13*C$42)/(1+$A44)^7-Inputs!$B$25)/Inputs!$B$8 | D44: =(NPV($A44,Model!$C$30:$I$30)+(Model!$I$13*D$42)/(1+$A44)^7-Inputs!$B$25)/Inputs!$B$8 | E44: =(NPV($A44,Model!$C$30:$I$30)+(Model!$I$13*E$42)/(1+$A44)^7-Inputs!$B$25)/Inputs!$B$8 | F44: =(NPV($A44,Model!$C$30:$I$30)+(Model!$I$13*F$42)/(1+$A44)^7-Inputs!$B$25)/Inputs!$B$8
A45: =Inputs!$B$39 | B45: =(NPV($A45,Model!$C$30:$I$30)+(Model!$I$13*B$42)/(1+$A45)^7-Inputs!$B$25)/Inputs!$B$8 | C45: =(NPV($A45,Model!$C$30:$I$30)+(Model!$I$13*C$42)/(1+$A45)^7-Inputs!$B$25)/Inputs!$B$8 | D45: =(NPV($A45,Model!$C$30:$I$30)+(Model!$I$13*D$42)/(1+$A45)^7-Inputs!$B$25)/Inputs!$B$8 | E45: =(NPV($A45,Model!$C$30:$I$30)+(Model!$I$13*E$42)/(1+$A45)^7-Inputs!$B$25)/Inputs!$B$8 | F45: =(NPV($A45,Model!$C$30:$I$30)+(Model!$I$13*F$42)/(1+$A45)^7-Inputs!$B$25)/Inputs!$B$8
A46: =Inputs!$B$39+0.01 | B46: =(NPV($A46,Model!$C$30:$I$30)+(Model!$I$13*B$42)/(1+$A46)^7-Inputs!$B$25)/Inputs!$B$8 | C46: =(NPV($A46,Model!$C$30:$I$30)+(Model!$I$13*C$42)/(1+$A46)^7-Inputs!$B$25)/Inputs!$B$8 | D46: =(NPV($A46,Model!$C$30:$I$30)+(Model!$I$13*D$42)/(1+$A46)^7-Inputs!$B$25)/Inputs!$B$8 | E46: =(NPV($A46,Model!$C$30:$I$30)+(Model!$I$13*E$42)/(1+$A46)^7-Inputs!$B$25)/Inputs!$B$8 | F46: =(NPV($A46,Model!$C$30:$I$30)+(Model!$I$13*F$42)/(1+$A46)^7-Inputs!$B$25)/Inputs!$B$8
A47: =Inputs!$B$39+0.02 | B47: =(NPV($A47,Model!$C$30:$I$30)+(Model!$I$13*B$42)/(1+$A47)^7-Inputs!$B$25)/Inputs!$B$8 | C47: =(NPV($A47,Model!$C$30:$I$30)+(Model!$I$13*C$42)/(1+$A47)^7-Inputs!$B$25)/Inputs!$B$8 | D47: =(NPV($A47,Model!$C$30:$I$30)+(Model!$I$13*D$42)/(1+$A47)^7-Inputs!$B$25)/Inputs!$B$8 | E47: =(NPV($A47,Model!$C$30:$I$30)+(Model!$I$13*E$42)/(1+$A47)^7-Inputs!$B$25)/Inputs!$B$8 | F47: =(NPV($A47,Model!$C$30:$I$30)+(Model!$I$13*F$42)/(1+$A47)^7-Inputs!$B$25)/Inputs!$B$8
A48: Cross-check: exit EV/EBITDA implied by Gordon TV (FY33E) | B48: =Model!C157/Model!I127 | C48: =Model!C43/Model!I13 | D48: =Model!C100/Model!I70
A49: Cross-check: perpetual growth implied by exit-multiple TV | B49: =(Model!C159*Inputs!$B$39-Model!I144)/(Model!C159+Model!I144) | C49: =(Model!C45*Inputs!$B$39-Model!I30)/(Model!C45+Model!I30) | D49: =(Model!C102*Inputs!$B$39-Model!I87)/(Model!C102+Model!I87)
A50: E. CHARTS
A115: F. KEY POINTS
A116: • | B116: FY26A revenue rose from ₹20,243 Cr to ₹54,364 Cr, helped by Blinkit’s dark-store expansion and the shift toward gross revenue recognition. I have not carried that step-change forward; growth moderates across the forecast period.
A117: • | B117: The margin build is driven by four operating levers: materials, employee costs, delivery and logistics, and marketing/other opex. Each driver is shown separately on the Inputs sheet.
A118: • | B118: Base-case FCFF is negative in FY27E as capex and taxes outrun the D&A add-back, then turns positive from FY28E. The valuation is terminal-value-heavy: the PV of the Gordon Growth terminal value is roughly 2.5x the PV of the explicit FCFF in the Base case.
A119: • | B119: Both terminal-value methods land below the current share price in the Bear and Base cases. Only the Bull-case exit-multiple value of about ₹320 approaches the ₹335.50 market price. The two methods also disagree with each other: Gordon Growth implies roughly 5x FY33E EBITDA, while the assumed exit multiples imply roughly 11-13% perpetual growth (see rows 48-49). Read together, the market appears to be pricing a stronger path than even this model's Bull case, or a materially lower discount rate.
A120: • | B120: Eternal is close to net cash at FY26A, so WACC is driven mainly by the cost of equity; capital structure has limited effect on the result. The D&A schedule runs off a depreciable base of ₹7,074 Cr (PP&E, CWIP, other intangibles and right-of-use lease assets), excluding ₹5,737 Cr of goodwill, which is not depreciated under Ind AS.
A121: • | B121: The sensitivity tables use live NPV and terminal-value formulas rather than Excel data tables, so they update automatically when the underlying assumptions change.

Sheet Inputs
A1: ETERNAL LTD (ZOMATO) — DCF MODEL: INPUT ASSUMPTIONS (₹ Crore unless stated)
A3: 1. COMPANY & MARKET DATA
A4: Company name | B4: Eternal Limited (formerly Zomato Limited)
A5: Ticker (NSE / BSE) | B5: ETERNAL / 543320
A6: Valuation date | B6: 24-Sep-2026
A7: Current share price (₹) | B7: 335.5 | K7: Source: NSE/BSE quote, 24-Sep-2026 (Screener.in).
A8: Diluted shares outstanding (Cr) | B8: 920 | K8: Diluted shares ≈ Equity share capital ₹919 Cr / face value ₹1 (FY26 balance sheet, Screener.in).
A9: Market capitalization (₹ Cr) | B9: =B7*B8
A11: 2. BASE YEAR (FY26A) ACTUALS — Source: Eternal FY26 audited consolidated financial statements
A12: Revenue from operations FY26A (₹ Cr) | B12: 54364 | K12: FY25A→FY26A revenue +168.6% YoY, driven by Blinkit quick-commerce dark-store scale-up and gross revenue recognition on the inventory-led model. Source: Eternal FY25 Annual Report (Medianama); Screener.in FY26 P&L.
A13: EBITDA (Adjusted operating profit) FY26A (₹ Cr) | B13: 1208 | K13: 'Operating Profit' per Screener.in = EBITDA (before D&A, interest, other income).
A14: EBITDA margin FY26A | B14: =B13/B12
A15: Depreciation & amortization FY26A (₹ Cr) | B15: 1597
A16: EBIT FY26A (₹ Cr) | B16: =B13-B15
A17: Other income FY26A (₹ Cr) | B17: 1396
A18: Interest expense FY26A (₹ Cr) | B18: 392
A19: Profit before tax FY26A (₹ Cr) | B19: =B16+B17-B18
A20: Effective tax rate FY26A | B20: 0.4 | K20: Elevated vs. statutory rate due to MAT/DTA true-ups; expected to normalize — see Section 4.
A21: Net profit FY26A (₹ Cr) | B21: =B19*(1-B20)
A22: Depreciable net block: PP&E + CWIP + intangibles + ROU assets, FY26A (₹ Cr) | B22: 7074 | K22: Net PP&E ₹2,033 Cr + CWIP ₹136 Cr + other intangibles ₹611 Cr + right-of-use (lease) assets ₹4,294 Cr = ₹7,074 Cr. Excludes goodwill of ₹5,737 Cr, which is not depreciated under Ind AS (tested for impairment only). The ₹12,811 Cr 'Fixed Assets' figure on Screener-style summaries bundles all five of these items including goodwill — using it as the D&A base overstates depreciation, the tax shield, and FCFF.
A23: Total borrowings / lease liabilities FY26A (₹ Cr) | B23: 4592 | K23: ~almost debt-free; D/E ≈0.11, mainly Ind AS 116 lease liabilities.
A24: Liquid investments + cash/bank balances FY26A (₹ Cr) | B24: 16356 | K24: Proxy for cash-like treasury (liquid investments); company holds net cash.
A25: Net debt / (net cash) FY26A (₹ Cr) | B25: =B23-B24
A26: Memo: Goodwill FY26A (₹ Cr, not depreciated — held at cost, tested for impairment) | B26: 5737 | K26: Memo only. Excluded from the D&A schedule and from the depreciable net block in B22.
A27: 3. WEIGHTED AVERAGE COST OF CAPITAL (WACC)
A28: Risk-free rate — India 10Y G-Sec yield on 24-Sep-2026 | B28: 0.07111 | K28: Approx. India 10-year G-Sec yield, 2026.
A29: Equity risk premium — India (Damodaran Jan-2026) | B29: 0.0708 | K29: Approx. India country equity risk premium (Damodaran-style estimate).
A30: Levered beta — 1-year observed market beta (Sep-2026) | B30: 1.36 | K30: Estimated for a high-growth, thin-margin consumer-internet platform; no long clean trading history post-2021 IPO, so proxied off global on-demand delivery/e-commerce peers (typically 1.2–1.5x).
A31: Cost of equity (CAPM) = Rf + β × ERP | B31: =B28+B30*B29
A32: Pre-tax cost of debt — modeled at 8.5% | B32: 0.085 | K32: Approx. cost on India corporate/lease borrowings given the rate environment.
A33: Tax rate for WACC (statutory, concessional regime) | B33: 0.252 | K33: Indian domestic company rate under Sec. 115BAA ≈25.17%.
A34: After-tax cost of debt | B34: =B32*(1-B33)
A35: Market value of equity (₹ Cr) | B35: =B9
A36: Market value of debt (₹ Cr) | B36: =B23
A37: Weight of equity | B37: =B35/(B35+B36)
A38: Weight of debt | B38: =B36/(B35+B36)
A39: WACC = We×Ke + Wd×Kd×(1-t) | B39: =B37*B31+B38*B34
A41: 4. SHARED OPERATING ASSUMPTIONS (accounting / financing drivers — held constant across scenarios)
A42: Driver | C42: FY27E | D42: FY28E | E42: FY29E | F42: FY30E | G42: FY31E | H42: FY32E | I42: FY33E
A43: Depreciation rate (% of opening net block) | C43: 0.15 | D43: 0.15 | E43: 0.15 | F43: 0.15 | G43: 0.15 | H43: 0.15 | I43: 0.15 | K43: Uses a 15% depreciation rate on opening net block as a simple blended assumption for dark stores, leasehold improvements, and IT assets. The rate is broadly consistent with FY26A D&A relative to the prior-year asset base.
A44: Net working capital (% of revenue) — 2.0% due inventory-led quick commerce | C44: 0.02 | D44: 0.02 | E44: 0.02 | F44: 0.02 | G44: 0.02 | H44: 0.02 | I44: 0.02 | K44: Keeps NWC at 2.0% of revenue. This is a simple assumption for a business with a low or near-neutral cash conversion cycle.
A45: Effective tax rate | C45: 0.3 | D45: 0.28 | E45: 0.26 | F45: 0.252 | G45: 0.252 | H45: 0.252 | I45: 0.252 | K45: Tax rate steps down from the FY26A effective rate of 40.0% toward the 25.2% statutory rate as one-off MAT/DTA effects normalize.
A46: New lease/debt additions (% of capex) | C46: 0.2 | D46: 0.2 | E46: 0.2 | F46: 0.2 | G46: 0.2 | H46: 0.2 | I46: 0.2 | K46: Portion of capex capitalized as new Ind AS 116 lease liabilities for dark-store/warehouse network additions.
A47: Debt repayment (% of opening debt) | C47: 0.18 | D47: 0.18 | E47: 0.18 | F47: 0.18 | G47: 0.18 | H47: 0.18 | I47: 0.18 | K47: Approximate average lease amortization rate on the opening lease-liability balance.
A49: 5. SCENARIO DRIVERS — BASE CASE
A50: FY27E Revenue (₹ Cr) | C50: FY27E | D50: FY28E | E50: FY29E | F50: FY30E | G50: FY31E | H50: FY32E | I50: FY33E
A51: Bear | B51: 82000 | C51: 0.65550732 | D51: 0.3 | E51: 0.22 | F51: 0.19 | G51: 0.16 | H51: 0.14 | I51: 0.12 | K51: Base case: revenue growth slows from the FY26A step-up as Blinkit scales and food delivery grows at a steadier pace. EBITDA margin reaches 13.0% by FY33E through lower materials, employee, and delivery costs as a share of revenue. Capex also moderates as the network matures.
A52: Base | B52: 90000 | C52: 0.655 | D52: 0.635 | E52: 0.615 | F52: 0.595 | G52: 0.575 | H52: 0.555 | I52: 0.535
A53: Bull | B53: 100000 | C53: 0.068 | D53: 0.066 | E53: 0.063 | F53: 0.06 | G53: 0.058 | H53: 0.055 | I53: 0.052
A54: Delivery & logistics expense (% of revenue) | C54: 0.118 | D54: 0.112 | E54: 0.108 | F54: 0.105 | G54: 0.102 | H54: 0.1 | I54: 0.098
A55: Marketing, technology & other opex (% of revenue) | C55: 0.114 | D55: 0.117 | E55: 0.124 | F55: 0.135 | G55: 0.15 | H55: 0.165 | I55: 0.185
A56: Capital expenditure (% of revenue) | C56: 0.045 | D56: 0.0425 | E56: 0.04 | F56: 0.0375 | G56: 0.035 | H56: 0.0325 | I56: 0.03
A57: Terminal growth rate (g), post FY33E | C57: 0.05
A58: Exit EV/EBITDA multiple (cross-check method) | C58: 14
A61: 6. SCENARIO DRIVERS — BULL CASE
A62: Driver | C62: FY27E | D62: FY28E | E62: FY29E | F62: FY30E | G62: FY31E | H62: FY32E | I62: FY33E
A63: Revenue growth % YoY | C63: 0.83945258 | D63: 0.35 | E63: 0.25 | F63: 0.21 | G63: 0.18 | H63: 0.16 | I63: 0.14 | K63: Bull case: Blinkit keeps gaining scale, food delivery remains resilient, and monetization improves across ads, Gold, and District. EBITDA margin reaches 14.5% by FY33E, with higher capex supporting faster dark-store expansion.
A64: Cost of materials/goods consumed (% of revenue) | C64: 0.65 | D64: 0.625 | E64: 0.6 | F64: 0.575 | G64: 0.555 | H64: 0.535 | I64: 0.52
A65: Employee benefit expense (% of revenue) | C65: 0.066 | D65: 0.063 | E65: 0.06 | F65: 0.056 | G65: 0.053 | H65: 0.05 | I65: 0.047
A66: Delivery & logistics expense (% of revenue) | C66: 0.116 | D66: 0.108 | E66: 0.103 | F66: 0.098 | G66: 0.094 | H66: 0.09 | I66: 0.088
A67: Marketing, technology & other opex (% of revenue) | C67: 0.118 | D67: 0.124 | E67: 0.132 | F67: 0.151 | G67: 0.168 | H67: 0.185 | I67: 0.2
A68: Capital expenditure (% of revenue) | C68: 0.05 | D68: 0.0475 | E68: 0.045 | F68: 0.0425 | G68: 0.04 | H68: 0.0375 | I68: 0.035
A69: Terminal growth rate (g), post FY33E | C69: 0.055
A70: Exit EV/EBITDA multiple (cross-check method) | C70: 16
A73: 7. SCENARIO DRIVERS — BEAR CASE
A74: Driver | C74: FY27E | D74: FY28E | E74: FY29E | F74: FY30E | G74: FY31E | H74: FY32E | I74: FY33E
A75: Revenue growth % YoY | C75: 0.50835111 | D75: 0.24 | E75: 0.16 | F75: 0.14 | G75: 0.12 | H75: 0.1 | I75: 0.08 | K75: Bear case: competition keeps pressure on pricing and delivery costs, while quick-commerce investment takes longer to pay back. EBITDA margin reaches 10.5% by FY33E, with lower capex and more conservative terminal assumptions.
A76: Cost of materials/goods consumed (% of revenue) | C76: 0.67 | D76: 0.66 | E76: 0.65 | F76: 0.64 | G76: 0.63 | H76: 0.62 | I76: 0.61
A77: Employee benefit expense (% of revenue) | C77: 0.073 | D77: 0.071 | E77: 0.069 | F77: 0.067 | G77: 0.064 | H77: 0.061 | I77: 0.058
A78: Delivery & logistics expense (% of revenue) | C78: 0.123 | D78: 0.119 | E78: 0.116 | F78: 0.113 | G78: 0.11 | H78: 0.107 | I78: 0.104
A79: Marketing, technology & other opex (% of revenue) | C79: 0.104 | D79: 0.105 | E79: 0.105 | F79: 0.105 | G79: 0.111 | H79: 0.117 | I79: 0.123
A80: Capital expenditure (% of revenue) | C80: 0.035 | D80: 0.0325 | E80: 0.03 | F80: 0.0275 | G80: 0.025 | H80: 0.0225 | I80: 0.02
A81: Terminal growth rate (g), post FY33E | C81: 0.045
A82: Exit EV/EBITDA multiple (cross-check method) | C82: 12

Sheet Model
A1: ETERNAL LTD (ZOMATO) — DCF MODEL: LINKED FINANCIAL PROJECTIONS (₹ Crore unless stated)
A3: SCENARIO 1 OF 3 — BASE CASE
A4: Line item | B4: FY26A | C4: FY27E | D4: FY28E | E4: FY29E | F4: FY30E | G4: FY31E | H4: FY32E | I4: FY33E
A5: Revenue | B5: =Inputs!$B$12 | C5: =Inputs!$B$52 | D5: =C5*(1+Inputs!D51) | E5: =D5*(1+Inputs!E51) | F5: =E5*(1+Inputs!F51) | G5: =F5*(1+Inputs!G51) | H5: =G5*(1+Inputs!H51) | I5: =H5*(1+Inputs!I51)
A6: Revenue growth % YoY | C6: =C5/B5-1 | D6: =Inputs!D51 | E6: =Inputs!E51 | F6: =Inputs!F51 | G6: =Inputs!G51 | H6: =Inputs!H51 | I6: =Inputs!I51
A8: Cost of materials/goods consumed | C8: =C5*Inputs!C52 | D8: =D5*Inputs!D52 | E8: =E5*Inputs!E52 | F8: =F5*Inputs!F52 | G8: =G5*Inputs!G52 | H8: =H5*Inputs!H52 | I8: =I5*Inputs!I52
A9: Employee benefit expense | C9: =C5*Inputs!C53 | D9: =D5*Inputs!D53 | E9: =E5*Inputs!E53 | F9: =F5*Inputs!F53 | G9: =G5*Inputs!G53 | H9: =H5*Inputs!H53 | I9: =I5*Inputs!I53
A10: Delivery & logistics expense | C10: =C5*Inputs!C54 | D10: =D5*Inputs!D54 | E10: =E5*Inputs!E54 | F10: =F5*Inputs!F54 | G10: =G5*Inputs!G54 | H10: =H5*Inputs!H54 | I10: =I5*Inputs!I54
A11: Marketing, technology & other opex | C11: =C5*Inputs!C55 | D11: =D5*Inputs!D55 | E11: =E5*Inputs!E55 | F11: =F5*Inputs!F55 | G11: =G5*Inputs!G55 | H11: =H5*Inputs!H55 | I11: =I5*Inputs!I55
A12: Total operating expenses | C12: =SUM(C8:C11) | D12: =SUM(D8:D11) | E12: =SUM(E8:E11) | F12: =SUM(F8:F11) | G12: =SUM(G8:G11) | H12: =SUM(H8:H11) | I12: =SUM(I8:I11)
A13: EBITDA | B13: =Inputs!$B$13 | C13: =C5-C12 | D13: =D5-D12 | E13: =E5-E12 | F13: =F5-F12 | G13: =G5-G12 | H13: =H5-H12 | I13: =I5-I12
A14: EBITDA margin % | B14: =B13/B5 | C14: =C13/C5 | D14: =D13/D5 | E14: =E13/E5 | F14: =F13/F5 | G14: =G13/G5 | H14: =H13/H5 | I14: =I13/I5
A16: Opening net block (PP&E) | C16: =B19 | D16: =C19 | E16: =D19 | F16: =E19 | G16: =F19 | H16: =G19 | I16: =H19
A17: Capital expenditure | C17: =C5*Inputs!C56 | D17: =D5*Inputs!D56 | E17: =E5*Inputs!E56 | F17: =F5*Inputs!F56 | G17: =G5*Inputs!G56 | H17: =H5*Inputs!H56 | I17: =I5*Inputs!I56
A18: Depreciation & amortization | B18: =Inputs!$B$15 | C18: =C16*Inputs!C43 | D18: =D16*Inputs!D43 | E18: =E16*Inputs!E43 | F18: =F16*Inputs!F43 | G18: =G16*Inputs!G43 | H18: =H16*Inputs!H43 | I18: =I16*Inputs!I43
A19: Closing net block (PP&E) | B19: =Inputs!$B$22 | C19: =C16+C17-C18 | D19: =D16+D17-D18 | E19: =E16+E17-E18 | F19: =F16+F17-F18 | G19: =G16+G17-G18 | H19: =H16+H17-H18 | I19: =I16+I17-I18
A21: EBIT | B21: =B13-B18 | C21: =C13-C18 | D21: =D13-D18 | E21: =E13-E18 | F21: =F13-F18 | G21: =G13-G18 | H21: =H13-H18 | I21: =I13-I18
A22: Effective tax rate % | B22: =Inputs!$B$20 | C22: =Inputs!C45 | D22: =Inputs!D45 | E22: =Inputs!E45 | F22: =Inputs!F45 | G22: =Inputs!G45 | H22: =Inputs!H45 | I22: =Inputs!I45
A23: Less: tax on EBIT | C23: =MAX(C21,0)*C22 | D23: =MAX(D21,0)*D22 | E23: =MAX(E21,0)*E22 | F23: =MAX(F21,0)*F22 | G23: =MAX(G21,0)*G22 | H23: =MAX(H21,0)*H22 | I23: =MAX(I21,0)*I22
A24: NOPAT | C24: =C21-C23 | D24: =D21-D23 | E24: =E21-E23 | F24: =F21-F23 | G24: =G21-G23 | H24: =H21-H23 | I24: =I21-I23
A26: Add: depreciation & amortization | C26: =C18 | D26: =D18 | E26: =E18 | F26: =F18 | G26: =G18 | H26: =H18 | I26: =I18
A27: Less: capital expenditure | C27: =-C17 | D27: =-D17 | E27: =-E17 | F27: =-F17 | G27: =-G17 | H27: =-H17 | I27: =-I17
A28: Net working capital balance | B28: =Inputs!$B$12*Inputs!$C$44 | C28: =C5*Inputs!C44 | D28: =D5*Inputs!D44 | E28: =E5*Inputs!E44 | F28: =F5*Inputs!F44 | G28: =G5*Inputs!G44 | H28: =H5*Inputs!H44 | I28: =I5*Inputs!I44
A29: Less: increase/(decrease) in NWC | C29: =-(C28-B28) | D29: =-(D28-C28) | E29: =-(E28-D28) | F29: =-(F28-E28) | G29: =-(G28-F28) | H29: =-(H28-G28) | I29: =-(I28-H28)
A30: Unlevered free cash flow (FCFF) | C30: =C24+C26+C27+C29 | D30: =D24+D26+D27+D29 | E30: =E24+E26+E27+E29 | F30: =F24+F26+F27+F29 | G30: =G24+G26+G27+G29 | H30: =H24+H26+H27+H29 | I30: =I24+I26+I27+I29
A32: Discount period (years) | C32: 1 | D32: 2 | E32: 3 | F32: 4 | G32: 5 | H32: 6 | I32: 7
A33: Discount factor @ WACC | C33: =1/(1+Inputs!$B$39)^C32 | D33: =1/(1+Inputs!$B$39)^D32 | E33: =1/(1+Inputs!$B$39)^E32 | F33: =1/(1+Inputs!$B$39)^F32 | G33: =1/(1+Inputs!$B$39)^G32 | H33: =1/(1+Inputs!$B$39)^H32 | I33: =1/(1+Inputs!$B$39)^I32
A34: PV of FCFF | C34: =C30*C33 | D34: =D30*D33 | E34: =E30*E33 | F34: =F30*F33 | G34: =G30*G33 | H34: =H30*H33 | I34: =I30*I33
A36: Opening debt / lease liabilities | C36: =B39 | D36: =C39 | E36: =D39 | F36: =E39 | G36: =F39 | H36: =G39 | I36: =H39
A37: Add: new lease liability additions | C37: =C17*Inputs!C46 | D37: =D17*Inputs!D46 | E37: =E17*Inputs!E46 | F37: =F17*Inputs!F46 | G37: =G17*Inputs!G46 | H37: =H17*Inputs!H46 | I37: =I17*Inputs!I46
A38: Less: repayments | C38: =C36*Inputs!C47 | D38: =D36*Inputs!D47 | E38: =E36*Inputs!E47 | F38: =F36*Inputs!F47 | G38: =G36*Inputs!G47 | H38: =H36*Inputs!H47 | I38: =I36*Inputs!I47
A39: Closing debt / lease liabilities | B39: =Inputs!$B$23 | C39: =C36+C37-C38 | D39: =D36+D37-D38 | E39: =E36+E37-E38 | F39: =F36+F37-F38 | G39: =G36+G37-G38 | H39: =H36+H37-H38 | I39: =I36+I37-I38
A40: Memo: interest expense | C40: =AVERAGE(C36,C39)*Inputs!$B$32 | D40: =AVERAGE(D36,D39)*Inputs!$B$32 | E40: =AVERAGE(E36,E39)*Inputs!$B$32 | F40: =AVERAGE(F36,F39)*Inputs!$B$32 | G40: =AVERAGE(G36,G39)*Inputs!$B$32 | H40: =AVERAGE(H36,H39)*Inputs!$B$32 | I40: =AVERAGE(I36,I39)*Inputs!$B$32
A42: Sum of PV of explicit FCFF (FY27E-FY33E) | C42: =SUM(C34:I34)
A43: Terminal value — Gordon Growth method | C43: =I30*(1+Inputs!$C$57)/(Inputs!$B$39-Inputs!$C$57)
A44: PV of terminal value — Gordon Growth | C44: =C43*I33
A45: Terminal value — Exit Multiple method | C45: =I13*Inputs!$C$58
A46: PV of terminal value — Exit Multiple | C46: =C45*I33
A47: Enterprise value — Gordon Growth method | C47: =C42+C44
A48: Enterprise value — Exit Multiple method | C48: =C42+C46
A49: Less: net debt / (net cash), FY26A | C49: =Inputs!$B$25
A50: Equity value — Gordon Growth method | C50: =C47-C49
A51: Equity value — Exit Multiple method | C51: =C48-C49
A52: Diluted shares outstanding (Cr) | C52: =Inputs!$B$8
A53: Implied share price — Gordon Growth (₹) | C53: =C50/C52
A54: Implied share price — Exit Multiple (₹) | C54: =C51/C52
A55: Current market price (₹) | C55: =Inputs!$B$7
A56: Upside / (downside) — Gordon Growth | C56: =C53/C55-1
A57: Upside / (downside) — Exit Multiple | C57: =C54/C55-1
A60: SCENARIO 2 OF 3 — BULL CASE
A61: Line item | B61: FY26A | C61: FY27E | D61: FY28E | E61: FY29E | F61: FY30E | G61: FY31E | H61: FY32E | I61: FY33E
A62: Revenue | B62: =Inputs!$B$12 | C62: =Inputs!$B$53 | D62: =C62*(1+Inputs!D63) | E62: =D62*(1+Inputs!E63) | F62: =E62*(1+Inputs!F63) | G62: =F62*(1+Inputs!G63) | H62: =G62*(1+Inputs!H63) | I62: =H62*(1+Inputs!I63)
A63: Revenue growth % YoY | C63: =C62/B62-1 | D63: =Inputs!D63 | E63: =Inputs!E63 | F63: =Inputs!F63 | G63: =Inputs!G63 | H63: =Inputs!H63 | I63: =Inputs!I63
A65: Cost of materials/goods consumed | C65: =C62*Inputs!C64 | D65: =D62*Inputs!D64 | E65: =E62*Inputs!E64 | F65: =F62*Inputs!F64 | G65: =G62*Inputs!G64 | H65: =H62*Inputs!H64 | I65: =I62*Inputs!I64
A66: Employee benefit expense | C66: =C62*Inputs!C65 | D66: =D62*Inputs!D65 | E66: =E62*Inputs!E65 | F66: =F62*Inputs!F65 | G66: =G62*Inputs!G65 | H66: =H62*Inputs!H65 | I66: =I62*Inputs!I65
A67: Delivery & logistics expense | C67: =C62*Inputs!C66 | D67: =D62*Inputs!D66 | E67: =E62*Inputs!E66 | F67: =F62*Inputs!F66 | G67: =G62*Inputs!G66 | H67: =H62*Inputs!H66 | I67: =I62*Inputs!I66
A68: Marketing, technology & other opex | C68: =C62*Inputs!C67 | D68: =D62*Inputs!D67 | E68: =E62*Inputs!E67 | F68: =F62*Inputs!F67 | G68: =G62*Inputs!G67 | H68: =H62*Inputs!H67 | I68: =I62*Inputs!I67
A69: Total operating expenses | C69: =SUM(C65:C68) | D69: =SUM(D65:D68) | E69: =SUM(E65:E68) | F69: =SUM(F65:F68) | G69: =SUM(G65:G68) | H69: =SUM(H65:H68) | I69: =SUM(I65:I68)
A70: EBITDA | B70: =Inputs!$B$13 | C70: =C62-C69 | D70: =D62-D69 | E70: =E62-E69 | F70: =F62-F69 | G70: =G62-G69 | H70: =H62-H69 | I70: =I62-I69
A71: EBITDA margin % | B71: =B70/B62 | C71: =C70/C62 | D71: =D70/D62 | E71: =E70/E62 | F71: =F70/F62 | G71: =G70/G62 | H71: =H70/H62 | I71: =I70/I62
A73: Opening net block (PP&E) | C73: =B76 | D73: =C76 | E73: =D76 | F73: =E76 | G73: =F76 | H73: =G76 | I73: =H76
A74: Capital expenditure | C74: =C62*Inputs!C68 | D74: =D62*Inputs!D68 | E74: =E62*Inputs!E68 | F74: =F62*Inputs!F68 | G74: =G62*Inputs!G68 | H74: =H62*Inputs!H68 | I74: =I62*Inputs!I68
A75: Depreciation & amortization | B75: =Inputs!$B$15 | C75: =C73*Inputs!C43 | D75: =D73*Inputs!D43 | E75: =E73*Inputs!E43 | F75: =F73*Inputs!F43 | G75: =G73*Inputs!G43 | H75: =H73*Inputs!H43 | I75: =I73*Inputs!I43
A76: Closing net block (PP&E) | B76: =Inputs!$B$22 | C76: =C73+C74-C75 | D76: =D73+D74-D75 | E76: =E73+E74-E75 | F76: =F73+F74-F75 | G76: =G73+G74-G75 | H76: =H73+H74-H75 | I76: =I73+I74-I75
A78: EBIT | B78: =B70-B75 | C78: =C70-C75 | D78: =D70-D75 | E78: =E70-E75 | F78: =F70-F75 | G78: =G70-G75 | H78: =H70-H75 | I78: =I70-I75
A79: Effective tax rate % | B79: =Inputs!$B$20 | C79: =Inputs!C45 | D79: =Inputs!D45 | E79: =Inputs!E45 | F79: =Inputs!F45 | G79: =Inputs!G45 | H79: =Inputs!H45 | I79: =Inputs!I45
A80: Less: tax on EBIT | C80: =MAX(C78,0)*C79 | D80: =MAX(D78,0)*D79 | E80: =MAX(E78,0)*E79 | F80: =MAX(F78,0)*F79 | G80: =MAX(G78,0)*G79 | H80: =MAX(H78,0)*H79 | I80: =MAX(I78,0)*I79
A81: NOPAT | C81: =C78-C80 | D81: =D78-D80 | E81: =E78-E80 | F81: =F78-F80 | G81: =G78-G80 | H81: =H78-H80 | I81: =I78-I80
A83: Add: depreciation & amortization | C83: =C75 | D83: =D75 | E83: =E75 | F83: =F75 | G83: =G75 | H83: =H75 | I83: =I75
A84: Less: capital expenditure | C84: =-C74 | D84: =-D74 | E84: =-E74 | F84: =-F74 | G84: =-G74 | H84: =-H74 | I84: =-I74
A85: Net working capital balance | B85: =Inputs!$B$12*Inputs!$C$44 | C85: =C62*Inputs!C44 | D85: =D62*Inputs!D44 | E85: =E62*Inputs!E44 | F85: =F62*Inputs!F44 | G85: =G62*Inputs!G44 | H85: =H62*Inputs!H44 | I85: =I62*Inputs!I44
A86: Less: increase/(decrease) in NWC | C86: =-(C85-B85) | D86: =-(D85-C85) | E86: =-(E85-D85) | F86: =-(F85-E85) | G86: =-(G85-F85) | H86: =-(H85-G85) | I86: =-(I85-H85)
A87: Unlevered free cash flow (FCFF) | C87: =C81+C83+C84+C86 | D87: =D81+D83+D84+D86 | E87: =E81+E83+E84+E86 | F87: =F81+F83+F84+F86 | G87: =G81+G83+G84+G86 | H87: =H81+H83+H84+H86 | I87: =I81+I83+I84+I86
A89: Discount period (years) | C89: 1 | D89: 2 | E89: 3 | F89: 4 | G89: 5 | H89: 6 | I89: 7
A90: Discount factor @ WACC | C90: =1/(1+Inputs!$B$39)^C89 | D90: =1/(1+Inputs!$B$39)^D89 | E90: =1/(1+Inputs!$B$39)^E89 | F90: =1/(1+Inputs!$B$39)^F89 | G90: =1/(1+Inputs!$B$39)^G89 | H90: =1/(1+Inputs!$B$39)^H89 | I90: =1/(1+Inputs!$B$39)^I89
A91: PV of FCFF | C91: =C87*C90 | D91: =D87*D90 | E91: =E87*E90 | F91: =F87*F90 | G91: =G87*G90 | H91: =H87*H90 | I91: =I87*I90
A93: Opening debt / lease liabilities | C93: =B96 | D93: =C96 | E93: =D96 | F93: =E96 | G93: =F96 | H93: =G96 | I93: =H96
A94: Add: new lease liability additions | C94: =C74*Inputs!C46 | D94: =D74*Inputs!D46 | E94: =E74*Inputs!E46 | F94: =F74*Inputs!F46 | G94: =G74*Inputs!G46 | H94: =H74*Inputs!H46 | I94: =I74*Inputs!I46
A95: Less: repayments | C95: =C93*Inputs!C47 | D95: =D93*Inputs!D47 | E95: =E93*Inputs!E47 | F95: =F93*Inputs!F47 | G95: =G93*Inputs!G47 | H95: =H93*Inputs!H47 | I95: =I93*Inputs!I47
A96: Closing debt / lease liabilities | B96: =Inputs!$B$23 | C96: =C93+C94-C95 | D96: =D93+D94-D95 | E96: =E93+E94-E95 | F96: =F93+F94-F95 | G96: =G93+G94-G95 | H96: =H93+H94-H95 | I96: =I93+I94-I95
A97: Memo: interest expense | C97: =AVERAGE(C93,C96)*Inputs!$B$32 | D97: =AVERAGE(D93,D96)*Inputs!$B$32 | E97: =AVERAGE(E93,E96)*Inputs!$B$32 | F97: =AVERAGE(F93,F96)*Inputs!$B$32 | G97: =AVERAGE(G93,G96)*Inputs!$B$32 | H97: =AVERAGE(H93,H96)*Inputs!$B$32 | I97: =AVERAGE(I93,I96)*Inputs!$B$32
A99: Sum of PV of explicit FCFF (FY27E-FY33E) | C99: =SUM(C91:I91)
A100: Terminal value — Gordon Growth method | C100: =I87*(1+Inputs!$C$69)/(Inputs!$B$39-Inputs!$C$69)
A101: PV of terminal value — Gordon Growth | C101: =C100*I90
A102: Terminal value — Exit Multiple method | C102: =I70*Inputs!$C$70
A103: PV of terminal value — Exit Multiple | C103: =C102*I90
A104: Enterprise value — Gordon Growth method | C104: =C99+C101
A105: Enterprise value — Exit Multiple method | C105: =C99+C103
A106: Less: net debt / (net cash), FY26A | C106: =Inputs!$B$25
A107: Equity value — Gordon Growth method | C107: =C104-C106
A108: Equity value — Exit Multiple method | C108: =C105-C106
A109: Diluted shares outstanding (Cr) | C109: =Inputs!$B$8
A110: Implied share price — Gordon Growth (₹) | C110: =C107/C109
A111: Implied share price — Exit Multiple (₹) | C111: =C108/C109
A112: Current market price (₹) | C112: =Inputs!$B$7
A113: Upside / (downside) — Gordon Growth | C113: =C110/C112-1
A114: Upside / (downside) — Exit Multiple | C114: =C111/C112-1
A117: SCENARIO 3 OF 3 — BEAR CASE
A118: Line item | B118: FY26A | C118: FY27E | D118: FY28E | E118: FY29E | F118: FY30E | G118: FY31E | H118: FY32E | I118: FY33E
A119: Revenue | B119: =Inputs!$B$12 | C119: =Inputs!$B$51 | D119: =C119*(1+Inputs!D75) | E119: =D119*(1+Inputs!E75) | F119: =E119*(1+Inputs!F75) | G119: =F119*(1+Inputs!G75) | H119: =G119*(1+Inputs!H75) | I119: =H119*(1+Inputs!I75)
...

Sheet Sources
A1: Eternal DCF — Sources & Assumption Audit | B1: Updated 26-Sep-2026; valuation date 24-Sep-2026
A2: Item | B2: Value / assumption | C2: Why used / explanation | D2: Source
A3: FY26 revenue | B3: 54364 | C3: Audited consolidated FY26 revenue; starting point for model. | D3: Eternal FY26 audited results / NSE filing
A4: FY26 EBITDA | B4: 1208 | C4: Historical adjusted operating profit used to anchor margin. | D4: Eternal FY26 audited results
A5: FY26 D&A | B5: 1597 | C5: Used to bridge EBITDA to EBIT and calculate FCFF. | D5: Eternal FY26 audited results
A6: FY26 liquid investments + cash | B6: 16356 | C6: 9,742 non-current investments + 5,091 current investments + 996 cash + 527 bank balances. | D6: Eternal FY26 audited balance sheet
A7: FY26 lease/borrowings | B7: 4592 | C7: Used for capital structure and equity bridge; largely lease liabilities. | D7: Eternal FY26 audited balance sheet
A8: FY26 net cash | B8: 11764 | C8: 16,356 liquid assets less 4,592 liabilities. Added to EV to get equity value. | D8: Derived from audited FY26 balance sheet
A9: 24-Sep-2026 share price | B9: 335.5 | C9: NSE closing price on valuation date; avoids mixing dates. | D9: S&P Global/StockAnalysis historical price
A10: Shares | B10: 920 | C10: Approx. Q1 FY27 diluted weighted-average shares / current share count. | D10: FY27 Q1 results / market data
A11: Risk-free rate | B11: 0.07111 | C11: India 10Y G-Sec yield on valuation date. | D11: Investing.com historical India 10Y data
A12: India ERP | B12: 0.0708 | C12: Damodaran Jan-2026 India equity risk premium dataset; close to original 7%. | D12: NYU Stern / Damodaran
A13: Beta | B13: 1.36 | C13: Observed 1-year beta around valuation date; used rather than an unsupported 1.35 estimate. | D13: Alloqo Sep-2026 market data
A14: Pre-tax debt cost | B14: 0.085 | C14: Rounded estimate near FY26 finance cost / lease-borrowing base; debt weight is small so sensitivity is limited. | D14: Derived / modeling assumption
A15: WACC | B15: =Inputs!B39 | C15: CAPM equity cost plus small after-tax debt component. | D15: Derived
A16: FY27 revenue — Base | B16: 90000 | C16: Q1 FY27 actual revenue was ₹20,211 Cr; model uses ₹90,000 Cr FY27 total to reflect continued growth while remaining below some street estimates. | D16: Eternal Q1 FY27 results + model judgment
A17: FY27 revenue — Bull | B17: 100000 | C17: Assumes stronger quick-commerce scale and food-delivery growth. | D17: Scenario assumption informed by Q1 FY27 trends
A18: FY27 revenue — Bear | B18: 82000 | C18: Assumes material deceleration after Q1 while still above FY26. | D18: Scenario assumption
A19: Terminal growth — Bear/Base/Bull | B19: 4.5% / 5.0% / 5.5% | C19: Keeps perpetual growth below/around long-run nominal growth rather than using 6.5% indefinitely. | D19: Modeling judgment
A20: Exit EV/EBITDA — Bear/Base/Bull | B20: 12x / 14x / 16x | C20: Cross-check only; multiples represent scenario ranges and should be compared with peer trading data. | D20: Modeling judgment
A21: NWC % revenue | B21: 0.02 | C21: Raised from 1% because inventory became much more important after the inventory-led quick-commerce shift. | D21: Eternal FY26 balance sheet + modeling judgment
A22: Capex % revenue | B22: 4.5%→3.0% Base | C22: Declines as dark-store rollout matures; Bull remains higher early, Bear lower. | D22: Scenario modeling assumption
A23: D&A % opening net block | B23: 0.15 | C23: Simple depreciation schedule; intentionally conservative and transparent rather than pretending to forecast asset classes separately. | D23: Modeling assumption
A24: FY28E growth () | B24: 30% / 35% / 24% (Base/Bull/Bear) | C24: Cell was blank , freezing FY28 revenue at the FY27 level in all scenarios. | D24: Modeling judgment
A25: Opening net block | B25: ₹7,074 Cr | C25: PP&E ₹2,033 Cr + CWIP ₹136 Cr + intangibles ₹611 Cr + right-of-use assets ₹4,294 Cr. Excludes ₹5,737 Cr goodwill, which Ind AS does not depreciate. | D25: Eternal FY26 audited balance sheet
A26: Calibration note (moved from Output) | B26: Valuation-date calibration: FY27 revenue starts from Q1 FY27 actuals and scenario assumptions; FY26 is historical anchor.
A27: Key data update (moved from Output) | B27: Key data update: share price ₹335.50, shares ~920 Cr, liquid assets ₹16,356 Cr, net cash ₹11,764 Cr, Rf 7.111%, ERP 7.08%, beta 1.36.
A28: Limitation: timing | B28: Full-year discounting from 31-Mar-2026 cash flows | C28: Valuation date is 24-Sep-2026 but FY27E is discounted as a full year and net cash is as of FY26A; no stub-period adjustment. | D28: Simplification
A29: Limitation: terminal year | B29: FY33E reinvestment reflects 12% growth | C29: Gordon TV grows FY33E FCFF at 4.5–5.5%; reinvestment not normalized to terminal growth, which is conservative. | D29: Simplification
A30: Limitation: beta | B30: 1.36 (1-year observed) | C30: Short, noisy history; a peer-based or regression beta would be more defensible. Cost of equity ≈ 16.7% drives the low Gordon value. | D30: Alloqo Sep-2026 market data
A31: Limitation: marketing opex | B31: Base rises 11.4% → 18.5% of revenue | C31: Caps FY33E EBITDA margin at 13%; deliberate reinvestment assumption that should be justified. | D31: Modeling judgment
A32: Data limitations & verification notes | B32: Q1 FY27 revenue ₹20,211 Cr; FY26 financials | C32: Cross-check against Eternal’s latest official filings before using the model for investment decisions. | D32: Eternal investor relations
A34: WACC defense | B34: 16.6% cost of capital | C34: High-growth quick-commerce business with elevated execution and competitive risk; higher cost of equity intentionally maintained. | D34: Model judgment
A35: Goodwill (excluded from D&A base) | B35: ₹5,737 Cr | C35: Not depreciated/amortized under Ind AS; tested annually for impairment. Held separately in Inputs B26 as a memo line. | D35: Eternal FY26 audited balance sheet
